{
  "name": "BarcodeSettings",
  "options": {
    "idInjection": false,
    "postgresql": {
      "schema": "public",
      "table": "_barcode_settings"
    }
  },
  "properties": {
    "id": {
      "type": "Number",
      "required": true,
      "length": null,
      "precision": 64,
      "scale": 0,
      "id": 1,
      "postgresql": {
        "columnName": "id",
        "dataType": "bigint",
        "dataLength": null,
        "dataPrecision": 64,
        "dataScale": 0,
        "nullable": "NO"
      }
    },
    "width": {
      "type": "Number",
      "required": true,
      "length": null,
      "precision": 64,
      "scale": 0,
      "postgresql": {
        "columnName": "width",
        "dataType": "bigint",
        "dataLength": null,
        "dataPrecision": 64,
        "dataScale": 0,
        "nullable": "NO"
      }
    },
    "height": {
      "type": "Number",
      "required": true,
      "length": null,
      "precision": 64,
      "scale": 0,
      "postgresql": {
        "columnName": "height",
        "dataType": "bigint",
        "dataLength": null,
        "dataPrecision": 64,
        "dataScale": 0,
        "nullable": "NO"
      }
    },
    "margin": {
      "type": "Number",
      "required": true,
      "length": null,
      "precision": 64,
      "scale": 0,
      "postgresql": {
        "columnName": "margin",
        "dataType": "bigint",
        "dataLength": null,
        "dataPrecision": 64,
        "dataScale": 0,
        "nullable": "NO"
      }
    },
    "barcodeHeight": {
      "type": "Number",
      "required": true,
      "length": null,
      "precision": 64,
      "scale": 0,
      "postgresql": {
        "columnName": "barcode_height",
        "dataType": "bigint",
        "dataLength": null,
        "dataPrecision": 64,
        "dataScale": 0,
        "nullable": "NO"
      }
    },
    "barcodeMultiplexer": {
      "type": "Number",
      "required": true,
      "length": null,
      "precision": 64,
      "scale": 0,
      "postgresql": {
        "columnName": "barcode_multiplexer",
        "dataType": "bigint",
        "dataLength": null,
        "dataPrecision": 64,
        "dataScale": 0,
        "nullable": "NO"
      }
    },
    "textLength": {
      "type": "Number",
      "required": true,
      "length": null,
      "precision": 64,
      "scale": 0,
      "postgresql": {
        "columnName": "text_length",
        "dataType": "bigint",
        "dataLength": null,
        "dataPrecision": 64,
        "dataScale": 0,
        "nullable": "NO"
      }
    },
    "textSize": {
      "type": "Number",
      "required": true,
      "length": null,
      "precision": 64,
      "scale": 0,
      "postgresql": {
        "columnName": "text_size",
        "dataType": "bigint",
        "dataLength": null,
        "dataPrecision": 64,
        "dataScale": 0,
        "nullable": "NO"
      }
    },
    "textSize2": {
      "type": "Number",
      "required": true,
      "length": null,
      "precision": 64,
      "scale": 0,
      "postgresql": {
        "columnName": "text_size2",
        "dataType": "bigint",
        "dataLength": null,
        "dataPrecision": 64,
        "dataScale": 0,
        "nullable": "NO"
      }
    },
    "printerLanguage": {
      "type": "String",
      "required": true,
      "length": 10,
      "precision": null,
      "scale": null,
      "postgresql": {
        "columnName": "printer_language",
        "dataType": "character varying",
        "dataLength": 10,
        "dataPrecision": null,
        "dataScale": null,
        "nullable": "NO"
      }
    },
    "price1": {
      "type": "String",
      "required": true,
      "length": 10,
      "precision": null,
      "scale": null,
      "postgresql": {
        "columnName": "price1",
        "dataType": "character varying",
        "dataLength": 10,
        "dataPrecision": null,
        "dataScale": null,
        "nullable": "NO"
      }
    },
    "price2": {
      "type": "String",
      "required": true,
      "length": 10,
      "precision": null,
      "scale": null,
      "postgresql": {
        "columnName": "price2",
        "dataType": "character varying",
        "dataLength": 10,
        "dataPrecision": null,
        "dataScale": null,
        "nullable": "NO"
      }
    },
    "language": {
      "type": "String",
      "required": true,
      "length": 50,
      "precision": null,
      "scale": null,
      "postgresql": {
        "columnName": "language",
        "dataType": "character varying",
        "dataLength": 50,
        "dataPrecision": null,
        "dataScale": null,
        "nullable": "NO"
      }
    },
    "currency": {
      "type": "String",
      "required": true,
      "length": 10,
      "precision": null,
      "scale": null,
      "postgresql": {
        "columnName": "currency",
        "dataType": "character varying",
        "dataLength": 10,
        "dataPrecision": null,
        "dataScale": null,
        "nullable": "NO"
      }
    },
    "currency2": {
      "type": "String",
      "required": true,
      "length": 10,
      "precision": null,
      "scale": null,
      "postgresql": {
        "columnName": "currency2",
        "dataType": "character varying",
        "dataLength": 10,
        "dataPrecision": null,
        "dataScale": null,
        "nullable": "NO"
      }
    },
    "brutto1": {
      "type": "Number",
      "required": true,
      "length": null,
      "precision": 64,
      "scale": 0,
      "postgresql": {
        "columnName": "brutto1",
        "dataType": "bigint",
        "dataLength": null,
        "dataPrecision": 64,
        "dataScale": 0,
        "nullable": "NO"
      }
    },
    "brutto2": {
      "type": "Number",
      "required": true,
      "length": null,
      "precision": 64,
      "scale": 0,
      "postgresql": {
        "columnName": "brutto2",
        "dataType": "bigint",
        "dataLength": null,
        "dataPrecision": 64,
        "dataScale": 0,
        "nullable": "NO"
      }
    },
    "userId": {
      "type": "Number",
      "required": true,
      "length": null,
      "precision": 64,
      "scale": 0,
      "postgresql": {
        "columnName": "user_id",
        "dataType": "bigint",
        "dataLength": null,
        "dataPrecision": 64,
        "dataScale": 0,
        "nullable": "NO"
      }
    },
    "note": {
      "type": "String",
      "required": true,
      "length": 100,
      "precision": null,
      "scale": null,
      "postgresql": {
        "columnName": "note",
        "dataType": "character varying",
        "dataLength": 100,
        "dataPrecision": null,
        "dataScale": null,
        "nullable": "NO"
      }
    },
    "note2": {
      "type": "String",
      "required": true,
      "length": 100,
      "precision": null,
      "scale": null,
      "postgresql": {
        "columnName": "note2",
        "dataType": "character varying",
        "dataLength": 100,
        "dataPrecision": null,
        "dataScale": null,
        "nullable": "NO"
      }
    },
    "noteSize": {
      "type": "Number",
      "required": true,
      "length": null,
      "precision": 64,
      "scale": 0,
      "postgresql": {
        "columnName": "note_size",
        "dataType": "bigint",
        "dataLength": null,
        "dataPrecision": 64,
        "dataScale": 0,
        "nullable": "NO"
      }
    },
    "noteSize2": {
      "type": "Number",
      "required": true,
      "length": null,
      "precision": 64,
      "scale": 0,
      "postgresql": {
        "columnName": "note_size2",
        "dataType": "bigint",
        "dataLength": null,
        "dataPrecision": 64,
        "dataScale": 0,
        "nullable": "NO"
      }
    },
    "deleted": {
      "type": "Number",
      "required": true,
      "length": null,
      "precision": 64,
      "scale": 0,
      "postgresql": {
        "columnName": "deleted",
        "dataType": "bigint",
        "dataLength": null,
        "dataPrecision": 64,
        "dataScale": 0,
        "nullable": "NO"
      }
    }
  }
}